<?xml version="1.0" encoding="UTF-8"?>
<magicdraw><statemachine humanType="Machine à Etat" icon="CoMAX_files/icon_16862246.jpg" id="_17_0_1_2_a9602c5_1377208063751_52622_12135"><ownedDiagram humanName="Diagramme avec Possesseur" mode="standard,expert"><diagram humanType="Diagramme" icon="CoMAX_files/icon_975527.jpg" name="Diagramme Etats Interface" refid="_17_0_1_2_a9602c5_1377208063751_446954_12134"/></ownedDiagram><ownedElement humanName="Elément avec Possesseur"><region humanType="Région" icon="CoMAX_files/icon_7261423.jpg" name="" refid="_17_0_1_2_a9602c5_1377208063751_29980_12136"/><signalevent humanType="Evénement de Signal" icon="CoMAX_files/icon_18968678.jpg" name="Commander Axe" refid="_17_0_1_2_a9602c5_1377209735060_785681_12284"/><diagram humanType="Diagramme" icon="CoMAX_files/icon_975527.jpg" name="Diagramme Etats Interface" refid="_17_0_1_2_a9602c5_1377208063751_446954_12134"/><signalevent humanType="Evénement de Signal" icon="CoMAX_files/icon_18968678.jpg" name="Ordre positionner Axe" refid="_17_0_1_2_a9602c5_1377208678782_291706_12203"/><signalevent humanType="Evénement de Signal" icon="CoMAX_files/icon_18968678.jpg" name="Selecteur Collaboration" refid="_17_0_1_2_a9602c5_1377208328795_96843_12185"/><signalevent humanType="Evénement de Signal" icon="CoMAX_files/icon_18968678.jpg" name="Selecteur Collaboration" refid="_17_0_1_2_a9602c5_1377208879616_238408_12221"/><signalevent humanType="Evénement de Signal" icon="CoMAX_files/icon_18968678.jpg" name="Selecteur Collaboration" refid="_17_0_1_2_a9602c5_1377209218870_14216_12247"/><signalevent humanType="Evénement de Signal" icon="CoMAX_files/icon_18968678.jpg" name="Selecteur Collaboration" refid="_17_0_1_2_a9602c5_1377209251568_156013_12254"/><signalevent humanType="Evénement de Signal" icon="CoMAX_files/icon_18968678.jpg" name="Selecteur Connexion" refid="_17_0_1_2_a9602c5_1377208151750_565992_12165"/><signalevent humanType="Evénement de Signal" icon="CoMAX_files/icon_18968678.jpg" name="Sortie" refid="_17_0_1_2_a9602c5_1377209775261_425681_12289"/><signalevent humanType="Evénement de Signal" icon="CoMAX_files/icon_18968678.jpg" name="Sélecteur Activation" refid="_17_0_1_2_a9602c5_1377208192388_900167_12173"/></ownedElement><namespace humanName="Espace de Nommage" humanType="Modèle" icon="CoMAX_files/icon_898702.jpg" name="Data" refid="eee_1045467100313_135436_1"/><isAbstract humanName="Est Abstrait">false</isAbstract><isActive humanName="Est Actif">false</isActive><isFinalSpecialization humanName="Est Final Spécialisation">false</isFinalSpecialization><isReentrant humanName="Est Ré-entrant">true</isReentrant><isLeaf humanName="Est une Feuille">false</isLeaf><event humanName="Evénement avec Possesseur"><signalevent humanType="Evénement de Signal" icon="CoMAX_files/icon_18968678.jpg" name="Commander Axe" refid="_17_0_1_2_a9602c5_1377209735060_785681_12284"/><signalevent humanType="Evénement de Signal" icon="CoMAX_files/icon_18968678.jpg" name="Ordre positionner Axe" refid="_17_0_1_2_a9602c5_1377208678782_291706_12203"/><signalevent humanType="Evénement de Signal" icon="CoMAX_files/icon_18968678.jpg" name="Selecteur Collaboration" refid="_17_0_1_2_a9602c5_1377208328795_96843_12185"/><signalevent humanType="Evénement de Signal" icon="CoMAX_files/icon_18968678.jpg" name="Selecteur Collaboration" refid="_17_0_1_2_a9602c5_1377208879616_238408_12221"/><signalevent humanType="Evénement de Signal" icon="CoMAX_files/icon_18968678.jpg" name="Selecteur Collaboration" refid="_17_0_1_2_a9602c5_1377209218870_14216_12247"/><signalevent humanType="Evénement de Signal" icon="CoMAX_files/icon_18968678.jpg" name="Selecteur Collaboration" refid="_17_0_1_2_a9602c5_1377209251568_156013_12254"/><signalevent humanType="Evénement de Signal" icon="CoMAX_files/icon_18968678.jpg" name="Selecteur Connexion" refid="_17_0_1_2_a9602c5_1377208151750_565992_12165"/><signalevent humanType="Evénement de Signal" icon="CoMAX_files/icon_18968678.jpg" name="Sortie" refid="_17_0_1_2_a9602c5_1377209775261_425681_12289"/><signalevent humanType="Evénement de Signal" icon="CoMAX_files/icon_18968678.jpg" name="Sélecteur Activation" refid="_17_0_1_2_a9602c5_1377208192388_900167_12173"/></event><member humanName="Membre"><region humanType="Région" icon="CoMAX_files/icon_7261423.jpg" name="" refid="_17_0_1_2_a9602c5_1377208063751_29980_12136"/></member><ownedMember humanName="Membre avec Possesseur"><region humanType="Région" icon="CoMAX_files/icon_7261423.jpg" name="" refid="_17_0_1_2_a9602c5_1377208063751_29980_12136"/></ownedMember><name humanName="Nom" mode="standard,expert">Diagramme Etats Interface</name><qualifiedName humanName="Nom Qualifié" mode="expert">Diagramme Etats Interface</qualifiedName><package humanName="Paquetage" humanType="Modèle" icon="CoMAX_files/icon_898702.jpg" name="Data" refid="eee_1045467100313_135436_1"/><owningPackage humanName="Paquetage de Possession" humanType="Modèle" icon="CoMAX_files/icon_898702.jpg" name="Data" refid="eee_1045467100313_135436_1"/><owner humanName="Possesseur" humanType="Modèle" icon="CoMAX_files/icon_898702.jpg" mode="standard,expert" name="Data" refid="eee_1045467100313_135436_1"/><region humanName="Région" mode="standard,expert"><region humanType="Région" icon="CoMAX_files/icon_7261423.jpg" name="" refid="_17_0_1_2_a9602c5_1377208063751_29980_12136"/></region><visibility humanName="Visibilité">public</visibility></statemachine></magicdraw>