<?xml version="1.0" encoding="UTF-8"?>
<magicdraw><informationflow humanType="Flux d'Information" icon="CoMAX_files/icon_16223293.jpg" id="_17_0_1_2_a9602c5_1375453240189_509427_15235"><target humanName="Cible"><flowport humanType="Flow Port" icon="CoMAX_files/icon_12980715.jpg" name="sans nom1" refid="_17_0_1_2_a9602c5_1375452881478_788475_15173"/></target><conveyed humanName="Convoyé" mode="standard,expert"><flowspecification humanType="Flow Specification" icon="CoMAX_files/icon_19107290.jpg" name="Energie mécanique (rotation)" refid="_17_0_1_2_a9602c5_1375452867316_948618_15164"/></conveyed><relatedElement humanName="Elément Relié"><flowport humanType="Flow Port" icon="CoMAX_files/icon_12980715.jpg" name="sans nom1" refid="_17_0_1_2_a9602c5_1375452893928_175864_15192"/><flowport humanType="Flow Port" icon="CoMAX_files/icon_12980715.jpg" name="sans nom1" refid="_17_0_1_2_a9602c5_1375452881478_788475_15173"/></relatedElement><namespace humanName="Espace de Nommage" humanType="Modèle" icon="CoMAX_files/icon_898702.jpg" name="CoMAX" refid="_17_0_1_2_a9602c5_1375363045372_480352_11572"/><informationTarget humanName="Information Cible" mode="standard,expert"><flowport humanType="Flow Port" icon="CoMAX_files/icon_12980715.jpg" name="sans nom1" refid="_17_0_1_2_a9602c5_1375452881478_788475_15173"/></informationTarget><name humanName="Nom" mode="standard,expert">flux pour Energie mécanique (rotation)</name><qualifiedName humanName="Nom Qualifié">CoMAX::flux pour Energie mécanique (rotation)</qualifiedName><owningPackage humanName="Paquetage de Possession" humanType="Modèle" icon="CoMAX_files/icon_898702.jpg" name="CoMAX" refid="_17_0_1_2_a9602c5_1375363045372_480352_11572"/><owner humanName="Possesseur" humanType="Modèle" icon="CoMAX_files/icon_898702.jpg" mode="standard,expert" name="CoMAX" refid="_17_0_1_2_a9602c5_1375363045372_480352_11572"/><realizingConnector humanName="Réalisation Connecteur"><connector humanType="Connecteur" icon="CoMAX_files/icon_9994156.jpg" isRelationship="true" name="" refid="_17_0_1_2_a9602c5_1375452912319_153688_15207"/></realizingConnector><source humanName="Source"><flowport humanType="Flow Port" icon="CoMAX_files/icon_12980715.jpg" name="sans nom1" refid="_17_0_1_2_a9602c5_1375452893928_175864_15192"/></source><informationSource humanName="Source d'Information" mode="standard,expert"><flowport humanType="Flow Port" icon="CoMAX_files/icon_12980715.jpg" name="sans nom1" refid="_17_0_1_2_a9602c5_1375452893928_175864_15192"/></informationSource><visibility humanName="Visibilité">public</visibility></informationflow></magicdraw>